<SOAP-ENV:Envelope xmlns:SOAP-ENV="http://schemas.xmlsoap.org/soap/envelope/"><SOAP-ENV:Header/><SOAP-ENV:Body><ns2:GetAddressesByAccountIdResponse xmlns:ns2="com.advantage.online.store.accountservice"><ns2:ShippingAddress><ns2:id>463</ns2:id><ns2:addressLine1>Kamchatka_Krai,Zarechnaya,96</ns2:addressLine1><ns2:city>Providence</ns2:city><ns2:country>UNITED_STATES_US</ns2:country><ns2:state>85/20/46</ns2:state><ns2:postalCode>987407168</ns2:postalCode><ns2:accountId>280016473</ns2:accountId></ns2:ShippingAddress><ns2:ShippingAddress><ns2:id>150</ns2:id><ns2:addressLine1>Kamchatka_Krai,Zarechnaya,96</ns2:addressLine1><ns2:city>Providence</ns2:city><ns2:country>UNITED_STATES_US</ns2:country><ns2:state>85/20/46</ns2:state><ns2:postalCode>171805751</ns2:postalCode><ns2:accountId>280016473</ns2:accountId></ns2:ShippingAddress></ns2:GetAddressesByAccountIdResponse></SOAP-ENV:Body></SOAP-ENV:Envelope>